betterconcurrent/__init__.py
betterconcurrent/_base.py
betterconcurrent/process.py
betterconcurrent/thread.py
betterconcurrent-0.0.1.post1.dist-info/LICENSE
betterconcurrent-0.0.1.post1.dist-info/METADATA
betterconcurrent-0.0.1.post1.dist-info/WHEEL
betterconcurrent-0.0.1.post1.dist-info/top_level.txt
betterconcurrent-0.0.1.post1.dist-info/RECORD
