Metadata-Version: 2.1
Name: betterconcurrent
Version: 0.0.1.post1
Summary: Better concurrent.futures for modern Python 3
Author-email: Nickolas Stathas <nickstathas@outlook.com>
Maintainer-email: Nickolas Stathas <nickstathas@outlook.com>
License: A. HISTORY OF THE SOFTWARE
Project-URL: Homepage, https://github.com/nistath/betterconcurrent
Keywords: concurrent,threading,futures
Classifier: Development Status :: 3 - Alpha
Classifier: Programming Language :: Python :: Implementation :: CPython
Classifier: Intended Audience :: Developers
Classifier: Intended Audience :: Information Technology
Classifier: Intended Audience :: Science/Research
Classifier: Programming Language :: Python :: 3
Classifier: Programming Language :: Python :: 3.9
Classifier: Programming Language :: Python :: 3.10
Classifier: Programming Language :: Python :: 3.11
Classifier: Programming Language :: Python :: 3 :: Only
Classifier: License :: OSI Approved :: Python Software Foundation License
Classifier: Topic :: Software Development :: Libraries
Requires-Python: >=3.0
License-File: LICENSE
Provides-Extra: test
Requires-Dist: pytest ; extra == 'test'
